ta_polars/__init__.py
ta_polars/_wrapping.py
ta_polars/momentum.py
ta_polars/others.py
ta_polars/trend.py
ta_polars/utils.py
ta_polars/volatility.py
ta_polars/volume.py
ta_polars/wrapper.py
ta_polars-0.1.1.dist-info/METADATA
ta_polars-0.1.1.dist-info/WHEEL
ta_polars-0.1.1.dist-info/RECORD
