Metadata-Version: 2.4
Name: ta-polars
Version: 0.1.1
Summary: TA-Lib-like technical indicators powered by Polars
Author: Yuvaraj
License: MIT
Requires-Python: >=3.9
Requires-Dist: polars>=1.0.0
